LICENCE.txt
README.txt
setup.py
ramesh/__init__.py
ramesh/achhahe.py
ramesh/anmolpanda.py
ramesh/cube.py
ramesh/fire.py
ramesh/minecrafts.py
ramesh.egg-info/PKG-INFO
ramesh.egg-info/SOURCES.txt
ramesh.egg-info/dependency_links.txt
ramesh.egg-info/top_level.txt