Metadata-Version: 1.1
Name: ramesh
Version: 0.1.0
Summary: A helper module with greatest power 
Home-page: UNKNOWN
Author: Ramesh
Author-email: rr188351@gmail.com
License: MIT
Keywords: tkinter
Platform: UNKNOWN
Classifier: Development Status :: 5 - Production/Stable
Classifier: Intended Audience :: Education
Classifier: Operating System :: Microsoft :: Windows :: Windows 10
Classifier: License :: OSI Approved :: MIT License
Classifier: Programming Language :: Python :: 3
